{
    "Enalapril": {
        "description" : "ACE inhibitor reducing blood pressure by preventing angiotensin II formation, promoting vasodilation and sodium excretion.",
        "recommended_dosage": {
            "adult" : 0,
            "paed" : 0,
            "neonate" : 0
        }
    },

    "Losartan": {
        "description" : "Angiotensin II receptor blocker (ARB) lowering blood pressure by inhibiting vasoconstriction and aldosterone secretion.",
        "recommended_dosage": {
            "adult" : 0,
            "paed" : 0,
            "neonate" : 0
        }
    },

    "Propranolol": {
        "description" : "Non-selective beta-blocker reducing heart rate and blood pressure by inhibiting \u03B21 and \u03B22 adrenergic receptors.",
        "recommended_dosage": {
            "adult" : 0,
            "paed" : 0,
            "neonate" : 0
        }
    },

    "Irbesartan": {
        "description" : "ARB blocking angiotensin II receptors, reducing vasoconstriction and aldosterone effects to lower blood pressure.",
        "recommended_dosage": {
            "adult" : 0,
            "paed" : 0,
            "neonate" : 0
        }
    },

    "Paracetamol": {
        "description" : "Analgesic and antipyretic inhibiting cyclooxygenase (COX) enzymes in the CNS, reducing pain and fever.",
        "recommended_dosage": {
            "adult" : 0,
            "paed" : 0,
            "neonate" : 0
        }
    }
}